riocore/plugins/stepdir/stepdir.v

module stepdir
    #(parameter PULSE_LEN = 2, parameter DIR_DELAY = 1)
    (
        input clk,
        input enable,
        input signed [31:0] velocity,
        output signed [31:0] position,
        output reg dir = 0,
        output reg step = 0,
        output en
    );
    wire dirFlag;
    assign dirFlag = (velocity >= 0);
    reg dir_changed = 0;
    reg [31:0] jointCounter = 32'd0;
    reg [31:0] velocityAbs = 32'd0;
    reg [31:0] pulseEnd = 32'd0;
    reg signed [31:0] positionMem = 32'd0;
    assign en = enable;
    assign position = positionMem;

    always @ (posedge clk) begin
        if (dirFlag) begin
            velocityAbs <= velocity;
        end else begin
            velocityAbs <= -velocity;
        end

        if (PULSE_LEN == 0) begin
            pulseEnd <= velocityAbs / 2;
        end else begin
            pulseEnd <= PULSE_LEN;
        end

        if ((velocity == 0 || enable == 0) && step == 0) begin
            jointCounter <= 0;
        end else if (jointCounter < velocityAbs) begin

            if (step == 0 && dir != dirFlag) begin
                dir <= dirFlag;
                dir_changed <= 1;
                jointCounter <= 0;

            end else if (dir_changed && jointCounter < DIR_DELAY) begin
                jointCounter <= jointCounter + 1;

            end else if (dir_changed) begin
                dir_changed <= 0;
                jointCounter <= 0;

            end else begin

                if (jointCounter == 0) begin
                    if (dir) begin
                        positionMem <= positionMem + 1;
                    end else begin
                        positionMem <= positionMem - 1;
                    end
                end

                if (jointCounter < pulseEnd) begin
                    step <= 1;
                end else begin
                    step <= 0;
                end

                jointCounter <= jointCounter + 1;

            end

        end else begin
            jointCounter <= 0;
        end
    end
endmodule

riocore/plugins/stepdir/testb.v

`timescale 1ns/100ps

module testb;
    reg clk = 0;
    always #1 clk = !clk;

    // pins
    wire step;
    wire dir;
    wire en;
    wire step2;
    wire dir2;
    wire en2;
    // interface
    reg signed [31:0] velocity = 32'd0;
    reg enable = 1;
    wire signed [31:0] position;
    wire signed [31:0] position2;

    initial begin
        $dumpfile("testb.vcd");
        $dumpvars(0, clk);
        // pins
        $dumpvars(1, step);
        $dumpvars(2, dir);
        $dumpvars(3, en);
        $dumpvars(4, step2);
        $dumpvars(5, dir2);
        $dumpvars(6, en2);
        // interface
        $dumpvars(7, velocity);
        $dumpvars(8, enable);
        $dumpvars(9, position);
        $dumpvars(10, position2);

        velocity = 50;
        #1000
        velocity = 0;
        #100
        velocity = -100;
        #1000
        velocity = -50;
        #1000
        velocity = 50;

        # 1000 $finish;
    end

    stepdir #(.PULSE_LEN(0), .DIR_DELAY(10)) stepdirstepdir (
        .clk(clk),
        .velocity(velocity),
        .enable(enable),
        .position(position),
        .step(step),
        .dir(dir),
        .en(en)
    );

    stepdir #(.PULSE_LEN(10), .DIR_DELAY(5)) stepdirstepdir2 (
        .clk(clk),
        .velocity(velocity),
        .enable(enable),
        .position(position2),
        .step(step2),
        .dir(dir2),
        .en(en2)
    );

endmodule

riocore/plugins/stepdir/testb.vcd
$date
	Tue Dec  3 16:52:47 2024
$end
$version
	Icarus Verilog
$end
$timescale
	100ps
$end
$scope module testb $end
$var reg 1 ! clk $end
$upscope $end
$scope module testb $end
$var wire 1 " step $end
$upscope $end
$scope module testb $end
$var wire 1 # dir $end
$upscope $end
$scope module testb $end
$var wire 1 $ en $end
$upscope $end
$scope module testb $end
$var wire 1 % step2 $end
$upscope $end
$scope module testb $end
$var wire 1 & dir2 $end
$upscope $end
$scope module testb $end
$var wire 1 ' en2 $end
$upscope $end
$scope module testb $end
$var reg 32 ( velocity [31:0] $end
$upscope $end
$scope module testb $end
$var reg 1 ) enable $end
$upscope $end
$scope module testb $end
$var wire 32 * position [31:0] $end
$upscope $end
$scope module testb $end
$var wire 32 + position2 [31:0] $end
$upscope $end
$enddefinitions $end
$comment Show the parameter values. $end
$dumpall
$end
#0
$dumpvars
b0 +
b0 *
1)
b110010 (
1'
0&
0%
1$
0#
0"
0!
$end
#10
1!
#20
0!
#30
1&
1#
1!
#40
0!
#50
1!
#60
0!
#70
1!
#80
0!
#90
1!
#100
0!
#110
1!
#120
0!
#130
1!
#140
0!
#150
1!
#160
0!
#170
1%
b1 +
1!
#180
0!
#190
1!
#200
0!
#210
1!
#220
0!
#230
1!
#240
0!
#250
1!
#260
0!
#270
1"
b1 *
1!
#280
0!
#290
1!
#300
0!
#310
1!
#320
0!
#330
1!
#340
0!
#350
1!
#360
0!
#370
0%
1!
#380
0!
#390
1!
#400
0!
#410
1!
#420
0!
#430
1!
#440
0!
#450
1!
#460
0!
#470
1!
#480
0!
#490
1!
#500
0!
#510
1!
#520
0!
#530
1!
#540
0!
#550
1!
#560
0!
#570
1!
#580
0!
#590
1!
#600
0!
#610
1!
#620
0!
#630
1!
#640
0!
#650
1!
#660
0!
#670
1!
#680
0!
#690
1!
#700
0!
#710
1!
#720
0!
#730
1!
#740
0!
#750
1!
#760
0!
#770
0"
1!
#780
0!
#790
1!
#800
0!
#810
1!
#820
0!
#830
1!
#840
0!
#850
1!
#860
0!
#870
1!
#880
0!
#890
1!
#900
0!
#910
1!
#920
0!
#930
1!
#940
0!
#950
1!
#960
0!
#970
1!
#980
0!
#990
1!
#1000
0!
#1010
1!
#1020
0!
#1030
1!
#1040
0!
#1050
1!
#1060
0!
#1070
1!
#1080
0!
#1090
1!
#1100
0!
#1110
1!
#1120
0!
#1130
1!
#1140
0!
#1150
1!
#1160
0!
#1170
1!
#1180
0!
#1190
1%
b10 +
1!
#1200
0!
#1210
1!
#1220
0!
#1230
1!
#1240
0!
#1250
1!
#1260
0!
#1270
1!
#1280
0!
#1290
1"
b10 *
1!
#1300
0!
#1310
1!
#1320
0!
#1330
1!
#1340
0!
#1350
1!
#1360
0!
#1370
1!
#1380
0!
#1390
0%
1!
#1400
0!
#1410
1!
#1420
0!
#1430
1!
#1440
0!
#1450
1!
#1460
0!
#1470
1!
#1480
0!
#1490
1!
#1500
0!
#1510
1!
#1520
0!
#1530
1!
#1540
0!
#1550
1!
#1560
0!
#1570
1!
#1580
0!
#1590
1!
#1600
0!
#1610
1!
#1620
0!
#1630
1!
#1640
0!
#1650
1!
#1660
0!
#1670
1!
#1680
0!
#1690
1!
#1700
0!
#1710
1!
#1720
0!
#1730
1!
#1740
0!
#1750
1!
#1760
0!
#1770
1!
#1780
0!
#1790
0"
1!
